<?xml version="1.0" encoding="UTF-8"?>
<objects serializationModel="Studio.02.02.00">
	<object class="MixerMaster" id="{b50e4391-b0c4-4b80-bdb6-173ad3a1ae20}">
		<property name="name">
			<value>Master Bus</value>
		</property>
		<relationship name="effectChain">
			<destination>{869c5cdb-5e16-4b62-9aeb-600617089872}</destination>
		</relationship>
		<relationship name="panner">
			<destination>{ae7426fd-30d7-4b39-a174-24a469e45bf8}</destination>
		</relationship>
		<relationship name="mixer">
			<destination>{35b7505c-40d7-4659-9fe1-318ec1041eb1}</destination>
		</relationship>
	</object>
	<object class="MixerBusEffectChain" id="{869c5cdb-5e16-4b62-9aeb-600617089872}">
		<relationship name="effects">
			<destination>{71cee581-f8db-4712-8902-3a598d2e6144}</destination>
		</relationship>
	</object>
	<object class="MixerBusPanner" id="{ae7426fd-30d7-4b39-a174-24a469e45bf8}">
		<property name="overridingOutputFormat">
			<value>2</value>
		</property>
	</object>
	<object class="MixerBusFader" id="{71cee581-f8db-4712-8902-3a598d2e6144}" />
</objects>
